{
	"configurations" : 
	[
		{
			"directories" : 
			[
				{
					"build" : ".",
					"childIndexes" : 
					[
						1,
						2
					],
					"minimumCMakeVersion" : 
					{
						"string" : "3.8"
					},
					"projectIndex" : 0,
					"source" : "."
				},
				{
					"build" : "practice-c",
					"minimumCMakeVersion" : 
					{
						"string" : "3.8"
					},
					"parentIndex" : 0,
					"projectIndex" : 0,
					"source" : "practice-c",
					"targetIndexes" : 
					[
						1
					]
				},
				{
					"build" : "arrays",
					"minimumCMakeVersion" : 
					{
						"string" : "3.8"
					},
					"parentIndex" : 0,
					"projectIndex" : 0,
					"source" : "arrays",
					"targetIndexes" : 
					[
						0
					]
				}
			],
			"name" : "Debug",
			"projects" : 
			[
				{
					"directoryIndexes" : 
					[
						0,
						1,
						2
					],
					"name" : "practice-c",
					"targetIndexes" : 
					[
						0,
						1
					]
				}
			],
			"targets" : 
			[
				{
					"directoryIndex" : 2,
					"id" : "main::@c94bb8d398953c4f7173",
					"jsonFile" : "target-main-Debug-12dbd2081b6f17574e8e.json",
					"name" : "main",
					"projectIndex" : 0
				},
				{
					"directoryIndex" : 1,
					"id" : "practice-c::@a3c711bd8b90001b40cc",
					"jsonFile" : "target-practice-c-Debug-81b3a690be75d577bf2e.json",
					"name" : "practice-c",
					"projectIndex" : 0
				}
			]
		}
	],
	"kind" : "codemodel",
	"paths" : 
	{
		"build" : "C:/Users/gonzapepe/Desktop/proyectos/practice-c/out/build/x64-Debug",
		"source" : "C:/Users/gonzapepe/Desktop/proyectos/practice-c"
	},
	"version" : 
	{
		"major" : 2,
		"minor" : 2
	}
}
